{
	"configurations" : 
	[
		{
			"directories" : 
			[
				{
					"build" : ".",
					"childIndexes" : 
					[
						1
					],
					"minimumCMakeVersion" : 
					{
						"string" : "3.16"
					},
					"projectIndex" : 0,
					"source" : "."
				},
				{
					"build" : "app",
					"childIndexes" : 
					[
						2,
						3,
						4
					],
					"minimumCMakeVersion" : 
					{
						"string" : "3.16"
					},
					"parentIndex" : 0,
					"projectIndex" : 0,
					"source" : "app"
				},
				{
					"build" : "app/ipc",
					"minimumCMakeVersion" : 
					{
						"string" : "3.16"
					},
					"parentIndex" : 1,
					"projectIndex" : 0,
					"source" : "app/ipc",
					"targetIndexes" : 
					[
						1
					]
				},
				{
					"build" : "app/components",
					"minimumCMakeVersion" : 
					{
						"string" : "3.16"
					},
					"parentIndex" : 1,
					"projectIndex" : 0,
					"source" : "app/components",
					"targetIndexes" : 
					[
						0
					]
				},
				{
					"build" : "app/threads",
					"minimumCMakeVersion" : 
					{
						"string" : "3.16"
					},
					"parentIndex" : 1,
					"projectIndex" : 0,
					"source" : "app/threads",
					"targetIndexes" : 
					[
						2
					]
				}
			],
			"name" : "Debug",
			"projects" : 
			[
				{
					"directoryIndexes" : 
					[
						0,
						1,
						2,
						3,
						4
					],
					"name" : "AGM850",
					"targetIndexes" : 
					[
						0,
						1,
						2
					]
				}
			],
			"targets" : 
			[
				{
					"directoryIndex" : 3,
					"id" : "components::@2a3d43a2e823b798d751",
					"jsonFile" : "target-components-Debug-916db0847fa5ef4dd908.json",
					"name" : "components",
					"projectIndex" : 0
				},
				{
					"directoryIndex" : 2,
					"id" : "ipc::@ef3dc89c71337de3085b",
					"jsonFile" : "target-ipc-Debug-493d7acbe8f8459c60d3.json",
					"name" : "ipc",
					"projectIndex" : 0
				},
				{
					"directoryIndex" : 4,
					"id" : "threads::@b3bb3d619fd98715b6fc",
					"jsonFile" : "target-threads-Debug-f9e9fb25b584e2fed4a0.json",
					"name" : "threads",
					"projectIndex" : 0
				}
			]
		}
	],
	"kind" : "codemodel",
	"paths" : 
	{
		"build" : "/home/user/project_dir/The_SSENs_FLIR_Seeker/src/software/build/debug",
		"source" : "/home/user/project_dir/The_SSENs_FLIR_Seeker/src/software"
	},
	"version" : 
	{
		"major" : 2,
		"minor" : 0
	}
}
